.hgignore
LICENSE.rst
ez_setup.py
setup.py
django_threaded_multihost.egg-info/PKG-INFO
django_threaded_multihost.egg-info/SOURCES.txt
django_threaded_multihost.egg-info/dependency_links.txt
django_threaded_multihost.egg-info/top_level.txt
docs/AUTHORS.rst
docs/CONTRIBUTING.rst
docs/INSTALL.rst
docs/TESTING.rst
tests/__init__.py
tests/manage.py
tests/settings.py
tests/urls.py
tests/model_tests/__init__.py
tests/model_tests/models.py
tests/model_tests/tests.py
threaded_multihost/__init__.py
threaded_multihost/fields.py
threaded_multihost/middleware.py
threaded_multihost/multihost_patch.py
threaded_multihost/sites.py
threaded_multihost/threadlocal_settings.py
threaded_multihost/threadlocals.py
threaded_multihost/utils.py